cumulus_library_kidney_transplant/.sqlfluff
cumulus_library_kidney_transplant/StudyBuilderConfig.json
cumulus_library_kidney_transplant/__init__.py
cumulus_library_kidney_transplant/casedef.py
cumulus_library_kidney_transplant/cohorts.py
cumulus_library_kidney_transplant/drug_eras.py
cumulus_library_kidney_transplant/fhir2sql.py
cumulus_library_kidney_transplant/filetool.py
cumulus_library_kidney_transplant/guard.py
cumulus_library_kidney_transplant/jaccard.py
cumulus_library_kidney_transplant/jsonifiers.py
cumulus_library_kidney_transplant/manifest.py
cumulus_library_kidney_transplant/manifest.toml
cumulus_library_kidney_transplant/study_builder.py
cumulus_library_kidney_transplant/study_population.py
cumulus_library_kidney_transplant/study_prefix.py
cumulus_library_kidney_transplant/vocab.py
cumulus_library_kidney_transplant/athena/irae__casedef.sql
cumulus_library_kidney_transplant/athena/irae__casedef_custom_csv.sql
cumulus_library_kidney_transplant/athena/irae__cohort_casedef.sql
cumulus_library_kidney_transplant/athena/irae__cohort_casedef_exclude.sql
cumulus_library_kidney_transplant/athena/irae__cohort_casedef_include.sql
cumulus_library_kidney_transplant/athena/irae__cohort_casedef_index.sql
cumulus_library_kidney_transplant/athena/irae__cohort_casedef_post.sql
cumulus_library_kidney_transplant/athena/irae__cohort_casedef_pre.sql
cumulus_library_kidney_transplant/athena/irae__cohort_casedef_timeline.sql
cumulus_library_kidney_transplant/athena/irae__cohort_diag_autoimmune.sql
cumulus_library_kidney_transplant/athena/irae__cohort_diag_cbc.sql
cumulus_library_kidney_transplant/athena/irae__cohort_diag_cmp.sql
cumulus_library_kidney_transplant/athena/irae__cohort_diag_creatinine.sql
cumulus_library_kidney_transplant/athena/irae__cohort_diag_custom.sql
cumulus_library_kidney_transplant/athena/irae__cohort_diag_diabetes.sql
cumulus_library_kidney_transplant/athena/irae__cohort_diag_gfr.sql
cumulus_library_kidney_transplant/athena/irae__cohort_diag_lft.sql
cumulus_library_kidney_transplant-0.3.0.dist-info/WHEEL
cumulus_library_kidney_transplant-0.3.0.dist-info/METADATA
cumulus_library_kidney_transplant-0.3.0.dist-info/RECORD
