Metadata-Version: 2.4
Name: cumulus-library-kidney-transplant
Version: 0.3.0
Summary: kidney transplant irAE (immuno related adverse events) related to immunosuppressive Medications post transplant
Requires-Python: >= 3.11
License-Expression: Apache-2.0
Classifier: Operating System :: OS Independent
Classifier: Programming Language :: Python :: 3
Classifier: Topic :: Software Development :: Libraries :: Python Modules
Requires-Dist: cumulus-library >= 5.1
Requires-Dist: pyrfc3339
Requires-Dist: sqlfluff >= 3, <4
Requires-Dist: tomli_w
Requires-Dist: black ; extra == "dev"
Requires-Dist: pylint ; extra == "dev"
Requires-Dist: pytest ; extra == "test"
Requires-Dist: pytest-cov ; extra == "test"
Requires-Dist: sqlglot[rs] ; extra == "test"
Project-URL: Documentation, https://docs.smarthealthit.org/cumulus/
Project-URL: Home, https://smarthealthit.org/cumulus-a-universal-sidecar-for-a-smart-learning-healthcare-system/
Project-URL: Source, https://github.com/smart-on-fhir/cumulus-library-kidney-transplant
Provides-Extra: dev
Provides-Extra: test
